{"sections":{"main":{"type":"main-product","blocks":{"title":{"type":"title","settings":{}},"price":{"type":"price","settings":{"text_size":"text-base"}},"variant_picker":{"type":"variant_picker","settings":{"option_style":"drop_down","hide_option_labels":false,"hide_sold_out_variants":false,"hide_unavailable_variants":false}},"quantity_selector":{"type":"quantity_selector","settings":{}},"buy_buttons":{"type":"buy_buttons","settings":{"enable_payment_button":true,"show_pickup_availability":true,"show_gift_card_recipient":false}},"description":{"type":"description","settings":{"enable_collapsible_tabs":false,"truncate_description":false,"max_words":30}},"smartsize_app_block_79LkCH":{"type":"shopify:\/\/apps\/smartsize\/blocks\/app-block\/465a43e0-6a1a-4d30-b82e-fe6118568705","settings":{}},"kiwi_size_chart_recommender_kiwi_sizing_UbEf7A":{"type":"shopify:\/\/apps\/kiwi-size-chart-recommender\/blocks\/kiwiSizing\/b7369922-bf15-44ce-a121-a22a8fcbc4b0","settings":{"product":"{{product}}"}}},"block_order":["title","price","variant_picker","quantity_selector","buy_buttons","description","smartsize_app_block_79LkCH","kiwi_size_chart_recommender_kiwi_sizing_UbEf7A"],"settings":{"desktop_media_width":"one-half","desktop_media_position":"left","two_media_per_row":true,"first_media_full_width":true,"variant_media_behavior":"scroll","always_show_product_featured_media_first":false,"enable_variant_media":true,"enable_image_zoom":false,"enable_video_looping":true,"max_width_of_content":"max-w-xl mx-auto","color_scheme":"scheme-6992d4f8-8106-425d-8c41-b8d7eb35ec96","override_header_footer_color_scheme":true}},"scrolling-text":{"type":"scrolling-text","settings":{"text":"you might also like","link":"","mobile_text_scale":2,"desktop_text_scale":2,"font":"font-body","speed":180,"direction":"normal","repeat_text":true,"separator":"&bullet;","separator_repeats":1,"spacing_between_repeated_separators":"","color_scheme":"scheme-af05f915-f93c-4377-8a96-4fc07bf9d45d"}},"related-products":{"type":"related-products","settings":{"heading":"","product_tile_type":"standard","limit":"4","products_per_row_desktop":"4","products_per_row_mobile":"1","enable_quick_buy":false,"quick_buy_button_style":"theme-button","color_scheme":"scheme-6992d4f8-8106-425d-8c41-b8d7eb35ec96"}}},"order":["main","scrolling-text","related-products"]}